ambio/EditDistance.py
ambio/__init__.py
ambio/algs.py
ambio/align.py
ambio/ambio.py
ambio/distance.py
ambio/match.py
ambio-0.5.2.dist-info/LICENSE
ambio-0.5.2.dist-info/METADATA
ambio-0.5.2.dist-info/WHEEL
ambio-0.5.2.dist-info/top_level.txt
ambio-0.5.2.dist-info/RECORD
