Metadata-Version: 2.1
Name: ambio
Version: 0.5.2
Summary: A lightweight Bioinformatics library
Home-page: https://github.com/albertomosconi/ambio
Author: Alberto Mosconi
Author-email: albertomaria.mosconi@gmail.com
License: UNKNOWN
Project-URL: Bug Tracker, https://github.com/albertomosconi/ambio/issues
Platform: UNKNOWN
Classifier: Programming Language :: Python :: 3
Classifier: License :: OSI Approved :: GNU General Public License v3 (GPLv3)
Classifier: Operating System :: OS Independent
Classifier: Natural Language :: English
Classifier: Topic :: Scientific/Engineering :: Bio-Informatics
Requires-Python: >=3.6
